kittylyst/__init__.py
kittylyst/callback.py
kittylyst/experiment.py
kittylyst/misc.py
kittylyst/runner.py
kittylyst-0.1.0.dist-info/LICENSE
kittylyst-0.1.0.dist-info/METADATA
kittylyst-0.1.0.dist-info/WHEEL
kittylyst-0.1.0.dist-info/top_level.txt
kittylyst-0.1.0.dist-info/RECORD
