Metadata-Version: 2.1
Name: kittylyst
Version: 0.1.0
Summary: A tiny Catalyst-like experiment runner framework on top of micrograd.
Home-page: https://github.com/scitator/kittylyst
Author: Sergey Kolesnikov
Author-email: scitator@gmail.com
License: UNKNOWN
Platform: UNKNOWN
Classifier: Programming Language :: Python :: 3
Classifier: License :: OSI Approved :: MIT License
Classifier: Operating System :: OS Independent
Requires-Python: >=3.6
Requires-Dist: micrograd (==0.1.0)
